space_stream-0.4.0.dist-info/licenses/LICENSE
spacestream/SpaceStreamApp.py
spacestream/SpaceStreamConfig.py
spacestream/SpaceStreamGraph.py
spacestream/WatchDog.py
spacestream/__init__.py
spacestream/__main__.py
spacestream/codec/DepthCodec.py
spacestream/codec/DepthCodecType.py
spacestream/codec/InverseHueColorization.py
spacestream/codec/LinearCodec.py
spacestream/codec/RealSenseColorizer.py
spacestream/codec/UniformHueColorization.py
spacestream/codec/__init__.py
spacestream/io/EnhancedJSONEncoder.py
spacestream/io/StreamInformation.py
spacestream/io/__init__.py
spacestream/nodes/ImageRectificationNode.py
spacestream/nodes/__init__.py
spacestream/ui/MainWindow.py
spacestream/ui/__init__.py
space_stream-0.4.0.dist-info/METADATA
space_stream-0.4.0.dist-info/WHEEL
space_stream-0.4.0.dist-info/entry_points.txt
space_stream-0.4.0.dist-info/top_level.txt
space_stream-0.4.0.dist-info/RECORD
