Metadata-Version: 2.4
Name: space-stream
Version: 0.4.0
Summary: Send RGB-D images over spout / syphon / NDI with visiongraph.
Home-page: https://github.com/cansik/space-stream
Author: Florian Bruggisser
Author-email: github@broox.ch
License: MIT License
License-File: LICENSE
Requires-Dist: configargparse
Requires-Dist: pyopengl
Requires-Dist: visiongraph[azure,fbs,media,mediapipe,numba,onnx-gpu,realsense]~=1.1.0.1
Requires-Dist: visiongraph-ndi~=0.2.0
Requires-Dist: visiongraph-ui~=0.3.0
Requires-Dist: duit[open3d]~=0.1.20
Requires-Dist: duit-osc~=0.3.0
Dynamic: author
Dynamic: author-email
Dynamic: description
Dynamic: description-content-type
Dynamic: home-page
Dynamic: license
Dynamic: license-file
Dynamic: requires-dist
Dynamic: summary
